pharmacophore/__init__.py
pharmacophore/constants.py
pharmacophore/draw.py
pharmacophore/pharmacophore.py
pharmacophore_toolkit-1.0.0.dist-info/LICENSE
pharmacophore_toolkit-1.0.0.dist-info/METADATA
pharmacophore_toolkit-1.0.0.dist-info/WHEEL
pharmacophore_toolkit-1.0.0.dist-info/RECORD
