Metadata-Version: 2.3
Name: pharmacophore-toolkit
Version: 1.0.0
Summary: A simple pharmacophore modeling toolkit
License: GPL-3.0-or-later
Author: Tony Eight Lin
Author-email: tonyelin@tmu.edu.tw
Requires-Python: >=3.9
Classifier: License :: OSI Approved :: GNU General Public License v3 or later (GPLv3+)
Classifier: Programming Language :: Python :: 3
Classifier: Programming Language :: Python :: 3.9
Classifier: Programming Language :: Python :: 3.10
Classifier: Programming Language :: Python :: 3.11
Classifier: Programming Language :: Python :: 3.12
Classifier: Programming Language :: Python :: 3.13
Provides-Extra: cairosvg
Requires-Dist: CairoSVG (>=2.7.1) ; extra == "cairosvg"
Requires-Dist: ipython (>=8)
Requires-Dist: ipywidgets (>=8)
Requires-Dist: matplotlib (>=3)
Requires-Dist: numpy (>=2.0.0)
Requires-Dist: pandas (>=2.0.0)
Requires-Dist: py3Dmol (>=2.4.2)
Requires-Dist: rdkit (>=2023.3.1)
Requires-Dist: tqdm
Project-URL: Repository, https://github.com/tlint101/pharmacophore-toolkit.git
